hybridbackend/libhybridbackend.so
hybridbackend/__init__.py
hybridbackend/run.py
hybridbackend/common/test.py
hybridbackend/common/atomic.cu.h
hybridbackend/common/logging.h
hybridbackend/common/macros.h
hybridbackend/common/profiler.h
hybridbackend/common/env.h
hybridbackend/common/Makefile
hybridbackend/common/__init__.py
hybridbackend/common/arrow.cc
hybridbackend/common/logging.cc
hybridbackend/common/arrow.h
hybridbackend/common/profiler.cc
hybridbackend/common/murmur3.cu.h
hybridbackend/common/pybind11.cc
hybridbackend/common/env.cc
hybridbackend/torch/__init__.py
hybridbackend/tensorflow/wraps.py
hybridbackend/tensorflow/libhybridbackend_tensorflow.so
hybridbackend/tensorflow/Makefile
hybridbackend/tensorflow/__init__.py
hybridbackend/tensorflow/data/iterators.py
hybridbackend/tensorflow/data/__init__.py
hybridbackend/tensorflow/data/dataframe.py
hybridbackend/tensorflow/data/tests/rebatch_dataset_seq_test.py
hybridbackend/tensorflow/data/tests/parquet_dataset_reshape_test.py
hybridbackend/tensorflow/data/tests/sync_replicas_dataset_test.py
hybridbackend/tensorflow/data/tests/parquet_dataset_ragged_test.py
hybridbackend/tensorflow/data/tests/rebatch_dataset_test.py
hybridbackend/tensorflow/data/tests/parquet_dataset_test.py
hybridbackend/tensorflow/data/tests/parquet_dataset_string_test.py
hybridbackend/tensorflow/data/tests/parquet_dataset_ragged_nested_test.py
hybridbackend/tensorflow/data/rebatch/rebatch_buffer.cc
hybridbackend/tensorflow/data/rebatch/buffer.h
hybridbackend/tensorflow/data/rebatch/__init__.py
hybridbackend/tensorflow/data/rebatch/dataset_v1.py
hybridbackend/tensorflow/data/rebatch/rebatch_dataset_v2.cc
hybridbackend/tensorflow/data/rebatch/dataset.py
hybridbackend/tensorflow/data/rebatch/dataset_v2.py
hybridbackend/tensorflow/data/sync/sync_replicas_dataset.cc
hybridbackend/tensorflow/data/sync/__init__.py
hybridbackend/tensorflow/data/sync/hook.py
hybridbackend_tf115_cu118-0.8.0.dev1678154818.dist-info/top_level.txt
hybridbackend_tf115_cu118-0.8.0.dev1678154818.dist-info/RECORD
hybridbackend_tf115_cu118-0.8.0.dev1678154818.dist-info/NOTICE
hybridbackend_tf115_cu118-0.8.0.dev1678154818.dist-info/LICENSE
hybridbackend_tf115_cu118-0.8.0.dev1678154818.dist-info/METADATA
hybridbackend_tf115_cu118-0.8.0.dev1678154818.dist-info/WHEEL
